# Nmap源码解析 28

# `liblua/ljumptab.h`

这段代码是一个Lua语言中的跳跃表（Jump Table）。它定义了一个名为vmdispatch的函数和三个预定义函数，以及它们的定义。

vmdispatch函数是一个Lua内置函数，它的参数x代表要跳转的目标行。通过使用goto语句，该函数会直接跳转到目标行处，而不需要使用标签（Break）或者编号（Dispatab）。因此，vmdispatch函数实际上是一个跳转表。

vmcase函数和预定义的三个函数（vmbreak，vmdispatch，vmcase）都是Lua定义的辅助函数，用于处理Lua和JavaScript的交互。它们的定义分别位于ljumptab.h文件中。这里简要介绍一下这三个函数的作用，以便于理解整个跳跃表的作用：

1. vmbreak：用于实现Lua和JavaScript之间的类型转换。当从Lua到JavaScript时，vmbreak函数将Lua中的一个引用类型转换为JavaScript中的一个引用类型。当从JavaScript到Lua时，vmbreak函数将JavaScript中的一个引用类型转换为Lua中的一个引用类型。

2. vmdispatch：主要用于实现Lua和JavaScript之间的跳转。当需要从一个地方跳转到另一个地方时，vmdispatch函数可以实现直接跳转到目标行，而不需要使用标签或者编号。

3. vmcase：这是一个辅助函数，用于将Lua中的一个用户定义类型转换为JavaScript中的一个用户定义类型。它类似于JavaScript中的作用域（Scope）：在Lua中，用户可以自定义作用域，而在JavaScript中，作用域是由var，let和const关键字来确定的。vmcase函数将Lua中的一个用户定义类型映射为JavaScript中的一个用户定义类型，使得Lua代码在JavaScript中更容易阅读和维护。


```cpp
/*
** $Id: ljumptab.h $
** Jump Table for the Lua interpreter
** See Copyright Notice in lua.h
*/


#undef vmdispatch
#undef vmcase
#undef vmbreak

#define vmdispatch(x)     goto *disptab[x];

#define vmcase(l)     L_##l:

```

这段代码定义了一个预处理指令 `vmbreak`，它使用 `vmfetch()` 函数取得当前指令的机器码，并调用 `vmdispatch()` 函数将机器码转换为汇编代码，以便更容易地理解。

接下来的 `const` 指针 `const disptab[NUM_OPCODES]` 定义了一个常量数组 `disptab`，它包含了 `NUM_OPCODES` 种不同的预处理指令。

然后，代码接下来定义了一个函数 `lopcodes.h`，但没有定义函数体，因此这个函数没有具体的作用。

最后，代码通过 `sed` 命令将 `lopcodes.h` 文件的内容替换为以下内容：

```cpp
#include <stdio.h>
#include <string.h>

#define OP_
#define OP_MOVE
#define OP_LOADI
#define OP_LOADF

static const void *const disptab[] = {
 &&L_OP_MOVE,
 &&L_OP_LOADI,
 &&L_OP_LOADF,
};
```

这段代码定义了一个预处理指令 `vmbreak`，将机器码通过 `vmfetch()` 和 `vmdispatch()` 函数转换为汇编代码，并定义了一个包含 `NUM_OPCODES` 种预处理指令的数组 `disptab`。这些预处理指令包括 `OP_`、`OP_MOVE`、`OP_LOADI` 和 `OP_LOADF`。此外，代码还定义了一个 `lopcodes.h` 文件，但没有定义函数体。


```cpp
#define vmbreak		vmfetch(); vmdispatch(GET_OPCODE(i));


static const void *const disptab[NUM_OPCODES] = {

#if 0
** you can update the following list with this command:
**
**  sed -n '/^OP_/\!d; s/OP_/\&\&L_OP_/ ; s/,.*/,/ ; s/\/.*// ; p'  lopcodes.h
**
#endif

&&L_OP_MOVE,
&&L_OP_LOADI,
&&L_OP_LOADF,
```

这段代码是一个C语言程序的伪代码，用于在程序中执行一系列逻辑判断。这里是一些关键部分的解释：

1. `&&L_OP_LOADK`: 如果`L_OP_LOADK`为真，则执行`LOADK`操作，并将结果存储在`L_OP_LOADK`中。
2. `&&L_OP_LOADKX`: 如果`L_OP_LOADK`为真，但`LOADKX`操作被禁止，则执行`LOADKX`操作，并将结果存储在`L_OP_LOADKX`中。
3. `&&L_OP_LOADFALSE`: 如果`L_OP_LOADFALSE`为真，则执行`LOADFALSE`操作，并将结果存储在`L_OP_LOADFALSE`中。
4. `&&L_OP_LFALSESKIP`: 如果`L_OP_LFALSESKIP`为真，则执行`LFALSESKIP`操作，并将结果存储在`L_OP_LFALSESKIP`中。
5. `&&L_OP_LOADTRUE`: 如果`L_OP_LOADTRUE`为真，则执行`LOADTRUE`操作，并将结果存储在`L_OP_LOADTRUE`中。
6. `&&L_OP_LOADNIL`: 如果`L_OP_LOADNIL`为真，则执行`LOADNIL`操作，并将结果存储在`L_OP_LOADNIL`中。
7. `&&L_OP_GETUPVAL`: 如果`L_OP_GETUPVAL`为真，则执行`GETUPVAL`操作，并将结果存储在`L_OP_GETUPVAL`中。
8. `&&L_OP_SETUPVAL`: 如果`L_OP_SETUPVAL`为真，则执行`SETUPVAL`操作，并将结果存储在`L_OP_SETUPVAL`中。
9. `&&L_OP_GETTABUP`: 如果`L_OP_GETTABUP`为真，则执行`GETTABUP`操作，并将结果存储在`L_OP_GETTABUP`中。
10. `&&L_OP_GETTABLE`: 如果`L_OP_GETTABLE`为真，则执行`GETTABLE`操作，并将结果存储在`L_OP_GETTABLE`中。
11. `&&L_OP_GETI`: 如果`L_OP_GETI`为真，则执行`GETI`操作，并将结果存储在`L_OP_GETI`中。
12. `&&L_OP_GETFIELD`: 如果`L_OP_GETFIELD`为真，则执行`GETFIELD`操作，并将结果存储在`L_OP_GETFIELD`中。
13. `&&L_OP_SETTABUP`: 如果`L_OP_SETTABUP`为真，则执行`SETTABUP`操作，并将结果存储在`L_OP_SETTABUP`中。
14. `&&L_OP_SETTABLE`: 如果`L_OP_SETTABLE`为真，则执行`SETTABLE`操作，并将结果存储在`L_OP_SETTABLE`中。
15. `&&L_OP_SETI`: 如果`L_OP_SETI`为真，则执行`SETI`操作，并将结果存储在`L_OP_SETI`中。


```cpp
&&L_OP_LOADK,
&&L_OP_LOADKX,
&&L_OP_LOADFALSE,
&&L_OP_LFALSESKIP,
&&L_OP_LOADTRUE,
&&L_OP_LOADNIL,
&&L_OP_GETUPVAL,
&&L_OP_SETUPVAL,
&&L_OP_GETTABUP,
&&L_OP_GETTABLE,
&&L_OP_GETI,
&&L_OP_GETFIELD,
&&L_OP_SETTABUP,
&&L_OP_SETTABLE,
&&L_OP_SETI,
```

这段代码是一个八位优先级测试，用于测试各种逻辑操作。逻辑操作包括：与（&&）、或（||）、非（非）和取反。八位优先级测试的结果存储在寄存器中，具体格式如下：

```cpp
&&L_OP_SETFIELD     % 输入为二进制数，最高位为 1，表示二进制的 7 位数据。
&&L_OP_NEWTABLE      % 输入为二进制数，最高位为 1，表示二进制的 7 位数据。
&&L_OP_SELF          % 输入为二进制数，最高位为 1，表示二进制的 7 位数据。
&&L_OP_ADDI        % 输入为二进制数，最高位为 1，表示二进制的 7 位数据。
&&L_OP_ADDK        % 输入为二进制数，最高位为 1，表示二进制的 7 位数据。
&&L_OP_SUBK        % 输入为二进制数，最高位为 1，表示二进制的 7 位数据。
&&L_OP_MULK        % 输入为二进制数，最高位为 1，表示二进制的 7 位数据。
&&L_OP_MODK        % 输入为二进制数，最高位为 1，表示二进制的 7 位数据。
&&L_OP_POWK        % 输入为二进制数，最高位为 1，表示二进制的 7 位数据。
&&L_OP_DIVK        % 输入为二进制数，最高位为 1，表示二进制的 7 位数据。
&&L_OP_IDIVK      % 输入为二进制数，最高位为 1，表示二进制的 7 位数据。
&&L_OP_BANDK        % 输入为二进制数，最高位为 1，表示二进制的 7 位数据。
&&L_OP_BORK        % 输入为二进制数，最高位为 1，表示二进制的 7 位数据。
&&L_OP_BXORK        % 输入为二进制数，最高位为 1，表示二进制的 7 位数据。
&&L_OP_SHRI          % 输入为十进制数，最高位为 1，表示整数除以 2^7。


```
&&L_OP_SETFIELD,
&&L_OP_NEWTABLE,
&&L_OP_SELF,
&&L_OP_ADDI,
&&L_OP_ADDK,
&&L_OP_SUBK,
&&L_OP_MULK,
&&L_OP_MODK,
&&L_OP_POWK,
&&L_OP_DIVK,
&&L_OP_IDIVK,
&&L_OP_BANDK,
&&L_OP_BORK,
&&L_OP_BXORK,
&&L_OP_SHRI,
```cpp

这段代码定义了一系列逻辑操作，包括加法、减法、乘法、取模、幂运算、除法和位运算等。这些操作符号以“&&”开头，说明它们都具有“与”或“且”优先级，即只有当所有的操作都为真时，整个表达式的结果才会为真。

例如，$(&&L_OP_SHLI && L_OP_ADD)将检查SHLI和ADD是否都为真，如果是，则执行SHLI操作并将结果存储在变量中。


```
&&L_OP_SHLI,
&&L_OP_ADD,
&&L_OP_SUB,
&&L_OP_MUL,
&&L_OP_MOD,
&&L_OP_POW,
&&L_OP_DIV,
&&L_OP_IDIV,
&&L_OP_BAND,
&&L_OP_BOR,
&&L_OP_BXOR,
&&L_OP_SHL,
&&L_OP_SHR,
&&L_OP_MMBIN,
&&L_OP_MMBINI,
```cpp

这段代码是一个C语言中的条件跳转语句，用于实现对表达式"&&L_OP_MMBINK,&&L_OP_UNM,&&L_OP_BNOT,&&L_OP_NOT,&&L_OP_LEN,&&L_OP_CONCAT,&&L_OP_CLOSE,&&L_OP_TBC,&&L_OP_JMP,&&L_OP_EQ,&&L_OP_LT,&&L_OP_LE,&&L_OP_EQK,&&L_OP_EQI,&&L_OP_LTI"进行判断并返回相应的结果。

具体来说，这个代码会判断表达式"&&L_OP_MMBINK"是否为真，如果是，就执行第一个语句块，否则跳转到第二个语句块。第二个语句块会判断表达式"&&L_OP_UNM"是否为真，如果是，就执行第三个语句块，否则跳转到第四个语句块。以此类推，直到判断表达式"&&L_OP_JMP"为真时，才会返回到第一个语句块。


```
&&L_OP_MMBINK,
&&L_OP_UNM,
&&L_OP_BNOT,
&&L_OP_NOT,
&&L_OP_LEN,
&&L_OP_CONCAT,
&&L_OP_CLOSE,
&&L_OP_TBC,
&&L_OP_JMP,
&&L_OP_EQ,
&&L_OP_LT,
&&L_OP_LE,
&&L_OP_EQK,
&&L_OP_EQI,
&&L_OP_LTI,
```cpp

这段代码是一个C语言中的条件运算符“&&”的集合，它们用于判断多个条件是否都为真时，输出一个符合条件的语句。

具体来说，这段代码如下：
```perl
&&L_OP_LEI ||
&&L_OP_GTI ||
&&L_OP_GEI ||
&&L_OP_TEST ||
&&L_OP_TESTSET ||
&&L_OP_CALL ||
&&L_OP_TAILCALL ||
&&L_OP_RETURN ||
&&L_OP_RETURN0 ||
&&L_OP_RETURN1 ||
&&L_OP_FORLOOP ||
&&L_OP_FORPREP ||
&&L_OP_TFORPREP ||
&&L_OP_TFORCALL ||
&&L_OP_TFORLOOP
```cpp
这段代码的作用是判断多个条件是否都为真，如果是，则输出符合条件的语句，否则不输出任何语句。


```
&&L_OP_LEI,
&&L_OP_GTI,
&&L_OP_GEI,
&&L_OP_TEST,
&&L_OP_TESTSET,
&&L_OP_CALL,
&&L_OP_TAILCALL,
&&L_OP_RETURN,
&&L_OP_RETURN0,
&&L_OP_RETURN1,
&&L_OP_FORLOOP,
&&L_OP_FORPREP,
&&L_OP_TFORPREP,
&&L_OP_TFORCALL,
&&L_OP_TFORLOOP,
```cpp

这是一段C语言代码，定义了五个&&L_OP_指令。

&&L_OP_SETLIST：设置列表指针为L_OP_SETLIST的地址。
&&L_OP_CLOSURE：关闭列表。
&&L_OP_VARARG：分配一个可变参数，即多个参数以逗号分隔。
&&L_OP_VARARGPREP：生成变量参数的程序段前缀。
&&L_OP_EXTRAARG：定义附加实参的标识。

这段代码定义了列表操作中的参数类型和参数前缀，以及输出了一些常见的列表操作。这些指令可能会被用于I/O操作、文件操作或者用户定义的程序中。


```
&&L_OP_SETLIST,
&&L_OP_CLOSURE,
&&L_OP_VARARG,
&&L_OP_VARARGPREP,
&&L_OP_EXTRAARG

};

```cpp

# `liblua/llex.c`

这段代码是一个C文件，它定义了一个名为"llex.c"的函数。该函数是Lua脚本中的一个函数，通常用于在Lua脚本中处理输入数据。

以下是函数的实现：

```c
#include "lprefix.h"


#include <locale.h>
#include <string.h>
```cpp

首先，该函数引入了两个头文件："lprefix.h"和Lua的"lua_core"。这些头文件可能包含一些用于Lua编程的通用函数和变量。

然后，该函数包含了两个定义：

```#define llex_c```cpp

```#define LUA_CORE```cpp

这两个定义似乎是在告诉编译器如何编译这个函数。其中，"#define llex_c"定义了一个名为"llex.c"的函数，而"#define LUA_CORE"定义了一个名为"LUA_CORE"的常量。

接下来，该函数包含了一个头文件包含：

```#include <locale.h>```cpp

```#include <string.h>```cpp

这两个头文件似乎是在引入`locale.h`和`string.h`函数，这些函数用于处理字符串输入数据。

最后，该函数定义了一个名为"my_double"的函数，该函数接受两个Lua类型参数：

```typedef struct {
   l_char *str;
   int len;
} my_double;```cpp

这个定义创建了一个名为"my_double"的Lua类型，该类型似乎用于存储字符串，并具有两个成员变量：

- 名为"str"，类型为"l_char"，表示一个指向字符类型的指针，可能是为了在Lua脚本中存放输入数据。
- 名为"len"，类型为"int"，表示一个整数，可能是用于记录字符串的长度。

该函数还定义了一个名为"init"的函数，该函数似乎用于初始化上述定义的"my_double"类型变量：

```int my_double_init(my_double *str, int len);```cpp

该函数接受两个参数：一个"my_double"类型的指针（由输入数据提供）和一个表示字符串长度的整数。它似乎将字符串的长度存储在整数变量"len"中，并将输入数据复制到字符指针"str"中。

然而，由于该函数没有定义任何函数体，因此我们无法确定该函数实际如何操作输入数据。


```
/*
** $Id: llex.c $
** Lexical Analyzer
** See Copyright Notice in lua.h
*/

#define llex_c
#define LUA_CORE

#include "lprefix.h"


#include <locale.h>
#include <string.h>

```cpp

这段代码是一个Lua编写的C头文件，它包含了多个Lua库函数，如lua_format，lua_ap捂，lua_缸，lua_主页等，用于在C语言中调用Lua函数和与Lua脚本交互。

具体来说，这段代码主要实现了以下功能：

1. 定义了一系列Lua函数
  ```
  // lua_format
  lua_format_export(C, "lua_format", "format_");

  // lua_ap捂
  lua_ap捂_export(C, "lua_ap捂", "ap捂");

  // lua_缸
  lua_缸_export(C, "lua_缸", "缸");

  // lua_主页
  lua_主页_export(C, "lua_主页", "主页");
  ```cpp

2. 引入了多个Lua库
  ```
  #include "lua.h"
  #include "lctype.h"
  #include "ldebug.h"
  #include "ldo.h"
  #include "lgc.h"
  #include "llex.h"
  #include "lobject.h"
  #include "lparser.h"
  #include "lstate.h"
  #include "lstring.h"
  #include "ltable.h"
  #include "lzio.h"
  ```cpp

3. 定义了多个函数指针
  ```
  lua_format_t format;
  lua_ap捂_t ap捂；
  lua_缸_t缸；
  lua_主页_t主页；
  ```cpp

4. 实现了Lua函数和Lua库的交互
  ```
  lua_format(format, "lua_format", "format_")
  lua_ap捂(ap捂， "lua_ap捂", "ap捂")
  lua_缸(缸， "lua_缸", "缸")
  lua_主页(主页， "lua_主页", "主页")
  ```cpp

这段代码中定义的函数指针可以在C语言中使用Lua提供的接口调用相应的Lua函数，从而实现与Lua脚本的交互。


```
#include "lua.h"

#include "lctype.h"
#include "ldebug.h"
#include "ldo.h"
#include "lgc.h"
#include "llex.h"
#include "lobject.h"
#include "lparser.h"
#include "lstate.h"
#include "lstring.h"
#include "ltable.h"
#include "lzio.h"



```cpp

这段代码是一个C语言中的预处理指令，定义了两个函数，next和currIsNewline。

next函数的作用是接收一个列表(List)对象，并返回该列表的下一个元素(如果是新的line则返回'\n')。其实现是通过调用另一个函数zgetc(ls->z)来获取该列表中的下一个元素，然后将该元素的值返回给调用者。

currIsNewline函数的作用是判断一个列表(List)对象是否为新的line。它使用了两个条件判断，第一个条件是ls->current是否为'\n'或者'\r'，如果是则返回true，否则返回false。

另外，该文件中还定义了一个常量数组luaX_tokens，该数组包含了Lua中的常见标识符，如and、break、do、else、elseif等。

最后，该文件中定义了一个名为luaX_set的函数，该函数的作用是设置某个Lua脚本中的某个变量为const类型的值。


```
#define next(ls)	(ls->current = zgetc(ls->z))



#define currIsNewline(ls)	(ls->current == '\n' || ls->current == '\r')


/* ORDER RESERVED */
static const char *const luaX_tokens [] = {
    "and", "break", "do", "else", "elseif",
    "end", "false", "for", "function", "goto", "if",
    "in", "local", "nil", "not", "or", "repeat",
    "return", "then", "true", "until", "while",
    "//", "..", "...", "==", ">=", "<=", "~=",
    "<<", ">>", "::", "<eof>",
    "<number>", "<integer>", "<name>", "<string>"
};


```cpp

这段代码是一个C语言中的预处理指令，定义了一个名为`save_and_next`的函数，其作用是接收一个字符数组`ls`，对其当前元素`ls->current`进行保存，并将下一个元素`next(ls)`作为参数返回。

该函数的具体实现如下：

1. 在函数定义之前，定义了一个名为`save`的函数，其作用是将一个字符数组`ls`保存到一个内存缓冲区`b`中。该函数的实现如下：

  ```
  Mbuffer *b = ls->buff;
  if (luaZ_bufflen(b) + 1 > luaZ_sizebuffer(b)) {
    size_t newsize;
    if (luaZ_sizebuffer(b) >= MAX_SIZE/2)
      lexerror(ls, "lexical element too long", 0);
    newsize = luaZ_sizebuffer(b) * 2;
    luaZ_resizebuffer(ls->L, b, newsize);
  }
  b->buffer[luaZ_bufflen(b)++] = cast_char(c);
  ```cpp

  其中，`ls->buff`指向的是`ls`字符数组的内存地址，`cast_char`函数将接收到的`c`字符转换成相应的ASCII码。

2. 在定义了`save`函数之后，定义了一个名为`lexerror`的函数，其作用是在`save`函数出现错误时进行错误提示。该函数的实现如下：

  ```
  static l_noret lexerror (LexState *ls, const char *msg, int token) {
      l_assert(ls != NULL);
      if (msg == NULL)
        return L_OK;
      return L_ERROR(L_MISC, strerror(msg), token);
  }
  ```cpp

  其中，`L_OK`表示函数返回成功，返回字符串`"L_OK"`作为结果；`L_ERROR`表示函数返回失败，返回错误信息作为结果。`strerror`函数将接收到的错误消息`msg`进行字符串比较，并返回错误代码。

3. 在定义了`save`和`lexerror`函数之后，未定义该文件中的任何其他函数，完整代码如下：

```
#include "example.h"
```cpp


```
#define save_and_next(ls) (save(ls, ls->current), next(ls))


static l_noret lexerror (LexState *ls, const char *msg, int token);


static void save (LexState *ls, int c) {
  Mbuffer *b = ls->buff;
  if (luaZ_bufflen(b) + 1 > luaZ_sizebuffer(b)) {
    size_t newsize;
    if (luaZ_sizebuffer(b) >= MAX_SIZE/2)
      lexerror(ls, "lexical element too long", 0);
    newsize = luaZ_sizebuffer(b) * 2;
    luaZ_resizebuffer(ls->L, b, newsize);
  }
  b->buffer[luaZ_bufflen(b)++] = cast_char(c);
}


```cpp



这两段代码是构成一个名为"luaX"的Lua脚本的一部分。它们的作用是在初始化Lua脚本时定义了一些常量和函数，以及在此过程中执行一些必要的转换和错误处理。

1. `luaX_init`函数的作用是在开始执行脚本之前设置一些默认值。具体来说，它将创建一个名为"env"的环境对象，其中包含一些已定义的环境名称。然后，它将收集所有保留字，并将它们存储在两个名为"reserved_words"的数组中。这个函数在脚本的开始和结束时都被调用，以确保任何用户定义的名称都是正确存储和管理的。

2. `luaX_token2str`函数的作用是将Lua中的一个保留字转换为字符串。根据保留字的类型，函数的实现方式会有所不同。如果是单字节符号，函数使用`lisprint`函数将保留字转换为字符串并返回。如果是控制字符或保留字，函数使用`<c>`格式化字符串语法来将保留字转换为字符串，并返回该字符串。在所有情况下，函数的行为是打印生成的字符串。

3. `__luaX_token2str`函数是一个从`luaX_token2str`函数中衍生出来的函数。它的作用是在保留字为字符串时执行相应的转换。它的实现方式与`luaX_token2str`函数类似，但使用的是`<c>`格式化字符串语法。它接收一个保留字作为参数，然后使用`<c>`语法将其转换为字符串，并返回该字符串。


```
void luaX_init (lua_State *L) {
  int i;
  TString *e = luaS_newliteral(L, LUA_ENV);  /* create env name */
  luaC_fix(L, obj2gco(e));  /* never collect this name */
  for (i=0; i<NUM_RESERVED; i++) {
    TString *ts = luaS_new(L, luaX_tokens[i]);
    luaC_fix(L, obj2gco(ts));  /* reserved words are never collected */
    ts->extra = cast_byte(i+1);  /* reserved word */
  }
}


const char *luaX_token2str (LexState *ls, int token) {
  if (token < FIRST_RESERVED) {  /* single-byte symbols? */
    if (lisprint(token))
      return luaO_pushfstring(ls->L, "'%c'", token);
    else  /* control character */
      return luaO_pushfstring(ls->L, "'<\\%d>'", token);
  }
  else {
    const char *s = luaX_tokens[token - FIRST_RESERVED];
    if (token < TK_EOS)  /* fixed format (symbols and reserved words)? */
      return luaO_pushfstring(ls->L, "'%s'", s);
    else  /* names, strings, and numerals */
      return s;
  }
}


```cpp

这两段代码是Lua中的函数，属于Lua的语法错误检查和处理。

第一个函数txtToken的作用是检查输入的字符串是否为命名标识符（TK_NAME、TK_STRING、TK_FLT、TK_INT中的一个），如果是，则将输入的字符串保存到变量ls中，并返回一个Lua字符串，该字符串由'“'和变量ls中缓冲区中的字符串组成。如果不是命名标识符，则返回Lua内置的错误处理函数luaX_token2str（第2个参数为输入的标识符，第3个参数为错误信息）。

第二个函数lexerror的作用是在出现语法错误时处理错误信息。当输入的标识符不是命名标识符时，会捕获到lexerror函数中，该函数将输入的标识符、错误消息和错误信息中的变量保存到ls中，然后使用luaO_pushfstring函数将错误消息输出到屏幕上，并使用luaD_throw函数抛出错误。错误信息是用%s格式化的字符串，其中%s代表错误信息，%n代表错误行号。


```
static const char *txtToken (LexState *ls, int token) {
  switch (token) {
    case TK_NAME: case TK_STRING:
    case TK_FLT: case TK_INT:
      save(ls, '\0');
      return luaO_pushfstring(ls->L, "'%s'", luaZ_buffer(ls->buff));
    default:
      return luaX_token2str(ls, token);
  }
}


static l_noret lexerror (LexState *ls, const char *msg, int token) {
  msg = luaG_addinfo(ls->L, msg, ls->source, ls->linenumber);
  if (token)
    luaO_pushfstring(ls->L, "%s near %s", msg, txtToken(ls, token));
  luaD_throw(ls->L, LUA_ERRSYNTAX);
}


```cpp

这段代码定义了一个名为`l_create_string`的函数，用于创建一个新的字符串，并将其存储在词法分析器的静态表中，以确保在编译过程中不会被删除或移动。该函数接受两个参数，一个是表示错误的错误句柄，另一个是要存储在表中的字符串参数。

具体来说，函数内部首先定义了一个名为`ls`的`LexState`结构体，用于跟踪当前的词法分析器和输入参数。接着，通过调用`lexerror`函数来获取输入参数中的错误信息，并将其存储在`ls->t.message`成员中。然后，使用`ls->t.cursor`成员作为参数，调用`luaX_syntaxerror`函数，将错误信息作为参数传递给该函数，并将错误类型为`LexError`的错误对象作为第一个参数传递。

最后，函数返回`LSR_OK`，表示操作成功。


```
l_noret luaX_syntaxerror (LexState *ls, const char *msg) {
  lexerror(ls, msg, ls->t.token);
}


/*
** Creates a new string and anchors it in scanner's table so that it
** will not be collected until the end of the compilation; by that time
** it should be anchored somewhere. It also internalizes long strings,
** ensuring there is only one copy of each unique string.  The table
** here is used as a set: the string enters as the key, while its value
** is irrelevant. We use the string itself as the value only because it
** is a TValue readly available. Later, the code generation can change
** this value.
*/
```cpp

这段代码是一个Lua脚本中的函数，它的参数包括一个LexState实例、一个表示字符串的C字符串和该字符串的长度。函数返回一个指向新创建的字符串的指针。

函数首先在LexState的L变量中创建一个新的字符串对象，然后使用luaS_newlstr函数将C字符串和给定的长度l转换为一个新的字符串对象ts。接下来，函数使用luaH_getstr函数获取该字符串对象的值，并检查它是否为空字符串。如果是，函数将ts保存为包含该值的TValue对象，并使用keystrval函数获取该值的保存位置，以便在函数返回后可以将其复制回对象。否则，函数使用s2v函数将L变量中top位置的堆栈空间分配给该字符串，并使用setsvalue函数将值分配给该位置，然后使用luaH_finishset函数将string元组包含ts，并暂时去除对象。

函数还包含一个使用luaC_checkGC函数来检查堆栈上是否有空对象，如果没有，则执行luaC_clear函数，然后将堆栈上的所有对象都返回，否则继续执行当前函数。


```
TString *luaX_newstring (LexState *ls, const char *str, size_t l) {
  lua_State *L = ls->L;
  TString *ts = luaS_newlstr(L, str, l);  /* create new string */
  const TValue *o = luaH_getstr(ls->h, ts);
  if (!ttisnil(o))  /* string already present? */
    ts = keystrval(nodefromval(o));  /* get saved copy */
  else {  /* not in use yet */
    TValue *stv = s2v(L->top++);  /* reserve stack space for string */
    setsvalue(L, stv, ts);  /* temporarily anchor the string */
    luaH_finishset(L, ls->h, stv, o, stv);  /* t[string] = string */
    /* table is not a metatable, so it does not need to invalidate cache */
    luaC_checkGC(L);
    L->top--;  /* remove string from stack */
  }
  return ts;
}


```cpp

这段代码是一个名为`inclinemounter`的函数，用于控制文本中行号的变化。其作用如下：

1. 首先定义了一个名为`inclinemounter`的函数，参数为`LexState`类型的指针`ls`。

2. 在函数内部，先定义了一个名为`old`的整数变量，用于记录当前行号。

3. 接着定义了一个名为`currIsNewline`的函数，用于判断当前是否处于换行符的情况。

4. 如果当前处于换行符的情况，函数会跳过当前行和换行符之间的所有内容。

5. 如果当前仍处于换行符的情况，函数会跳过当前行和换行符之间的所有内容，并在新行继续输出内容。

6. 如果指针`ls`所指向的行号已经达到了`MAX_INT`的值，函数会抛出一个`LexError`类型的异常，指出当前的行号超出了可以处理的最大行数。

7. 在函数内部，每次循环都会根据当前的行号，判断是否需要进行换行操作。如果需要，函数会根据当前的行号输出一个新的行，并跳过换行符。

8. 如果当前行号已经达到了`MAX_INT`的值，函数会抛出一个`LexError`类型的异常，指出当前的行号超出了可以处理的最大行数。


```
/*
** increment line number and skips newline sequence (any of
** \n, \r, \n\r, or \r\n)
*/
static void inclinenumber (LexState *ls) {
  int old = ls->current;
  lua_assert(currIsNewline(ls));
  next(ls);  /* skip '\n' or '\r' */
  if (currIsNewline(ls) && ls->current != old)
    next(ls);  /* skip '\n\r' or '\r\n' */
  if (++ls->linenumber >= MAX_INT)
    lexerror(ls, "chunk has too many lines", 0);
}


```cpp

这段代码是一个Lua脚本中的函数，它的作用是设置输入流中的第一个字符的输入格式的Lua变量。

具体来说，它首先定义了输入流中的第一个字符的Lua变量（ls.current）为第一个字符（即输入格式的第一个字符），然后设置了一些辅助变量（如lookahead.token，fs，linenumber等），以便在后续的处理中使用。接着，它将输入流中的第一个字符的Lua变量（ls.token）初始化为0，然后将输入格式的下一个字符（即第二个字符）的Lua变量（ls.L）赋值给输入流中的第一个字符的Lua变量（ls.current）。

最后，它初始化了输入流中的第一个字符的输入格式（即使用了ZIO类型的库，使用了always an交接方式，并设置了no look-ahead token），并将输入流中的第一个字符的输入格式（即使用了always an交接方式）初始化为TK_EOS。


```
void luaX_setinput (lua_State *L, LexState *ls, ZIO *z, TString *source,
                    int firstchar) {
  ls->t.token = 0;
  ls->L = L;
  ls->current = firstchar;
  ls->lookahead.token = TK_EOS;  /* no look-ahead token */
  ls->z = z;
  ls->fs = NULL;
  ls->linenumber = 1;
  ls->lastline = 1;
  ls->source = source;
  ls->envn = luaS_newliteral(L, LUA_ENV);  /* get env name */
  luaZ_resizebuffer(ls->L, ls->buff, LUA_MINBUFFER);  /* initialize buffer */
}



```cpp

这是一个 C 语言中的语法分析器，主要用来处理识别语法树中的剩余字符(即不是 ',' 也不是 '%')的符号'.'。

具体来说，这个程序的作用是定义了一个名为 `check_next1` 的函数，用于在剩余字符的语法树中查找下一个可以分析的符号的位置。如果当前字符是语法树中剩余字符的下一个，函数返回 1，否则返回 0。

函数的实现比较简单，直接判断当前字符是否是下一个剩余字符，如果是则返回 1，否则返回 0。


```
/*
** =======================================================
** LEXICAL ANALYZER
** =======================================================
*/


static int check_next1 (LexState *ls, int c) {
  if (ls->current == c) {
    next(ls);
    return 1;
  }
  else return 0;
}


```cpp

这段代码是一个Lua脚本，它的目的是检查给定的字符是否属于一个给定的字符串集合，并将检查结果存储在本地。

代码中定义了一个名为 check_next2 的函数，它接受一个指向字符串集合的指针变量 set，以及当前输入字符的变量 ls。函数内部首先检查给定的字符是否属于字符串集合的第一个字符或者第二个字符，如果是，就调用 save_and_next 函数并将结果存储在 ls 中，然后返回 1；否则返回 0。

这段代码的作用是判断给定的字符是否属于预先定义好的字符串集合中，并将检查结果存储在本地。它主要用于在需要时检查给定的字符是否属于预先定义好的字符串集合中，从而可以方便地在应用程序中使用预定义好的字符串。


```
/*
** Check whether current char is in set 'set' (with two chars) and
** saves it
*/
static int check_next2 (LexState *ls, const char *set) {
  lua_assert(set[2] == '\0');
  if (ls->current == set[0] || ls->current == set[1]) {
    save_and_next(ls);
    return 1;
  }
  else return 0;
}


/* LUA_NUMBER */
```cpp

This is a C implementation that reads a number as a literal from input. The number can include digits, exponential marks "e+" or "e-", and optional signs "+" or "-". The input is compared to a known pattern that has a flexible format.

The `read_numeral` function takes a LexState instance and a SemInfo instance. It reads the current character from the input, which is either a digit or a semicolon. If the first character is a digit, it checks if it is a valid exponent and updates the `expo` variable accordingly. If the first character is a semicolon, it checks if it is followed by a valid exponent and an optional exponent sign.

The function returns the appropriate data type of the number: `TK_INT` for an integer value or `TK_FLT` for a floating-point value, based on whether it is formatted correctly. If the input is invalid, it throws an error.


```
/*
** This function is quite liberal in what it accepts, as 'luaO_str2num'
** will reject ill-formed numerals. Roughly, it accepts the following
** pattern:
**
**   %d(%x|%.|([Ee][+-]?))* | 0[Xx](%x|%.|([Pp][+-]?))*
**
** The only tricky part is to accept [+-] only after a valid exponent
** mark, to avoid reading '3-4' or '0xe+1' as a single number.
**
** The caller might have already read an initial dot.
*/
static int read_numeral (LexState *ls, SemInfo *seminfo) {
  TValue obj;
  const char *expo = "Ee";
  int first = ls->current;
  lua_assert(lisdigit(ls->current));
  save_and_next(ls);
  if (first == '0' && check_next2(ls, "xX"))  /* hexadecimal? */
    expo = "Pp";
  for (;;) {
    if (check_next2(ls, expo))  /* exponent mark? */
      check_next2(ls, "-+");  /* optional exponent sign */
    else if (lisxdigit(ls->current) || ls->current == '.')  /* '%x|%.' */
      save_and_next(ls);
    else break;
  }
  if (lislalpha(ls->current))  /* is numeral touching a letter? */
    save_and_next(ls);  /* force an error */
  save(ls, '\0');
  if (luaO_str2num(luaZ_buffer(ls->buff), &obj) == 0)  /* format error? */
    lexerror(ls, "malformed number", TK_FLT);
  if (ttisinteger(&obj)) {
    seminfo->i = ivalue(&obj);
    return TK_INT;
  }
  else {
    lua_assert(ttisfloat(&obj));
    seminfo->r = fltvalue(&obj);
    return TK_FLT;
  }
}


```cpp

此代码是一个名为`skip_sep`的函数，用于处理输入序列中的分号(`=`)和换行符(`<br>`)，返回适当的数量。

函数的参数是一个`LexState`对象，代表当前解析状态，函数首先读取一个序列`[[=]=][]=`或`[[=]=]`，并忽略最后一个分号，然后开始处理其中的分号和换行符。

函数的具体实现包括以下几步：

1. 如果序列只有一个分号或一个换行符，函数将返回1。

2. 如果序列中包含两个分号，函数将返回2。

3. 如果序列中包含两个换行符，函数将返回1。

4. 如果序列中包含多个分号或多个换行符，函数将返回0。

5. 函数最后通过返回序列解析状态中的分号数量或总括号数量来得到最终结果。

该函数的作用是读取一个序列，如果是正确的序列，则返回其中的分号数量，如果不是正确的序列，则返回1或0。


```
/*
** read a sequence '[=*[' or ']=*]', leaving the last bracket. If
** sequence is well formed, return its number of '='s + 2; otherwise,
** return 1 if it is a single bracket (no '='s and no 2nd bracket);
** otherwise (an unfinished '[==...') return 0.
*/
static size_t skip_sep (LexState *ls) {
  size_t count = 0;
  int s = ls->current;
  lua_assert(s == '[' || s == ']');
  save_and_next(ls);
  while (ls->current == '=') {
    save_and_next(ls);
    count++;
  }
  return (ls->current == s) ? count + 2
         : (count == 0) ? 1
         : 0;
}


```cpp

这段代码是一个名为 `read_long_string` 的函数，属于 `luadoc` 库。它的作用是读取一个长字符串，并对字符串中的每一行进行处理。以下是该函数的详细解释：

1. 函数参数说明：
  - `ls`：当前 `LexState` 对象的引用，包含当前行号 `line` 和字符串当前位置 `current`。
  - `seminfo`：一个 `SemInfo` 对象，用于存储当前读取到的字符串信息，包括分隔符 `sep`、当前行数 `line_num`、错误信息 `error` 等。
  - `sep`：一个 `size_t` 类型的参数，用于存储当前字符串中的分隔符。

2. 函数实现：
  - 初始化函数行号为 0，即在函数输出时提供错误信息。
  - 如果当前行是新的换行符，则跳过它。
  - 进入一个无限循环，处理字符串中的每一行。
  - 对于每一行，根据当前行的类型执行不同的操作：
    - 如果当前行是错误符 `EOZ`，则先存储错误信息，然后跳转到下一个行。
    - 如果当前行是字符串结束符 `']`，则跳过当前行，因为已经处理完整个字符串。
    - 如果当前行是换行符 `\n` 或 `\r`，则将换行符周围的空格存入 `ls` 对象，然后继续处理下一行。
    - 如果当前行是字符串中的某个字符，则需要根据当前的 `sep` 决定如何处理。如果 `sep` 没有定义，则需要保留该字符，否则会将该字符转换为小写并将其转义。
    - 对于换行符和错误符，会自动跳转到下一行，否则会继续处理下一行。

3. 函数结束：
  - 如果 `seminfo` 被定义且 `sep` 被处理完，则将 `seminfo` 中的 `ts` 值计算出来，用于在输出时提供完整的字符串信息。

这段代码的作用是读取一个长字符串，并对每一行进行处理。其中，分隔符 `sep` 用于将字符串中的每一行分割为独立的部分，并对每一行执行不同的操作。如果当前行是换行符或错误符，则忽略该行。如果当前行是字符串中的某个字符，则需要根据当前的 `sep` 决定如何处理。


```
static void read_long_string (LexState *ls, SemInfo *seminfo, size_t sep) {
  int line = ls->linenumber;  /* initial line (for error message) */
  save_and_next(ls);  /* skip 2nd '[' */
  if (currIsNewline(ls))  /* string starts with a newline? */
    inclinenumber(ls);  /* skip it */
  for (;;) {
    switch (ls->current) {
      case EOZ: {  /* error */
        const char *what = (seminfo ? "string" : "comment");
        const char *msg = luaO_pushfstring(ls->L,
                     "unfinished long %s (starting at line %d)", what, line);
        lexerror(ls, msg, TK_EOS);
        break;  /* to avoid warnings */
      }
      case ']': {
        if (skip_sep(ls) == sep) {
          save_and_next(ls);  /* skip 2nd ']' */
          goto endloop;
        }
        break;
      }
      case '\n': case '\r': {
        save(ls, '\n');
        inclinenumber(ls);
        if (!seminfo) luaZ_resetbuffer(ls->buff);  /* avoid wasting space */
        break;
      }
      default: {
        if (seminfo) save_and_next(ls);
        else next(ls);
      }
    }
  } endloop:
  if (seminfo)
    seminfo->ts = luaX_newstring(ls, luaZ_buffer(ls->buff) + sep,
                                     luaZ_bufflen(ls->buff) - 2 * sep);
}


```cpp

这两段代码定义了两个静态函数：esccheck 和 gethexa。

esccheck函数的作用是在遇到预期的输入时，对其进行错误处理。如果输入为空，函数将保存当前输入并尝试下一个输入，同时使用保存的错误消息。如果输入为空，函数将会抛出异常，并将状态机设置为EOZ，以便在后续处理中继续前进。

gethexa函数的作用是获取一个十六进制数字，并将其返回。它将首先尝试获取一个输入，并将其传递给 esccheck 函数。如果 esccheck 函数返回的值不是数字，函数将返回-1，并将状态机设置为EOZ，以便在后续处理中继续前进。

总的来说，这两个函数都是辅助函数，用于在输入获取过程中处理异常和错误。


```
static void esccheck (LexState *ls, int c, const char *msg) {
  if (!c) {
    if (ls->current != EOZ)
      save_and_next(ls);  /* add current to buffer for error message */
    lexerror(ls, msg, TK_STRING);
  }
}


static int gethexa (LexState *ls) {
  save_and_next(ls);
  esccheck (ls, lisxdigit(ls->current), "hexadecimal digit expected");
  return luaO_hexavalue(ls->current);
}


```cpp

这两段代码是Lua脚本中用于从输入流中读取十六进制和UTF-8编码文本的功能。

`readhexaesc`函数的作用是读取一个十六进制字符串，并将其转换为相应的Lua数据类型(比如整数或字符串)。它通过使用两个辅助函数`gethexa`和`getutf8`来读取输入字符串中的十六进制字符。`gethexa`函数将输入字符串中的十六进制字符转换为一个Lua整数，而`getutf8`函数将输入字符串中的十六进制字符转换为一个Lua字符串。

`readhexaesc`函数的输入参数是一个指向LexState结构的变量`ls`，代表输入流。函数的返回值是一个整数类型的变量，代表读取的十六进制字符串。

`readutf8esc`函数的作用类似于`readhexaesc`，但它是用于读取UTF-8编码文本。它将输入流中的字符一个一个地读取，并检查读取的字符是否符合UTF-8编码的规范。它通过使用一个辅助函数`getutf8`来读取输入流中的UTF-8编码字符。

`getutf8`函数的输入参数也是一个指向LexState结构的变量`ls`，代表输入流。函数的返回值是一个`unsigned long`类型的变量，代表读取的UTF-8编码文本。

`readutf8esc`函数的辅助函数`getutf8`将输入流中的字符一个一个地读取，并检查读取的字符是否符合UTF-8编码的规范。如果读取到一个不符合规范的字符(比如'\u')，函数将返回一个错误信息。


```
static int readhexaesc (LexState *ls) {
  int r = gethexa(ls);
  r = (r << 4) + gethexa(ls);
  luaZ_buffremove(ls->buff, 2);  /* remove saved chars from buffer */
  return r;
}


static unsigned long readutf8esc (LexState *ls) {
  unsigned long r;
  int i = 4;  /* chars to be removed: '\', 'u', '{', and first digit */
  save_and_next(ls);  /* skip 'u' */
  esccheck(ls, ls->current == '{', "missing '{'");
  r = gethexa(ls);  /* must have at least one digit */
  while (cast_void(save_and_next(ls)), lisxdigit(ls->current)) {
    i++;
    esccheck(ls, r <= (0x7FFFFFFFu >> 4), "UTF-8 value too large");
    r = (r << 4) + luaO_hexavalue(ls->current);
  }
  esccheck(ls, ls->current == '}', "missing '}'");
  next(ls);  /* skip '}' */
  luaZ_buffremove(ls->buff, i);  /* remove saved chars from buffer */
  return r;
}


```cpp

这两段代码是Java中的两个函数，它们的目的是帮助用户处理UTF-8编码字符串。

utf8esc函数的作用是将输入的UTF-8编码字符串转换为字符，并提供了一些辅助操作。它接受一个LexState对象，和一个字符数组，数组长度为UTF8BUFFSZ。函数内部首先定义了一个名为buff的字符数组，用于存储输入的UTF-8编码字符串。接着，通过调用LuaO_utf8esc函数，将输入的UTF-8编码字符串转换为字符，并存储到buff数组中。最后，遍历buff数组，将读取到的字符添加到输入的字符数组中。

readdecesc函数的作用是将输入的ASCII编码字符串转换为UTF-8编码字符串，并提供了一些辅助操作。它接受一个LexState对象和一个整数变量r，用于表示输入的ASCII编码字符串的转义字符数。函数内部首先循环读取输入的字符，直到读取到第3个字符为止。接着，使用save_and_next函数，将当前的字符传递给下一个辅助函数，然后使用esccheck函数检查当前是否为ASCII转义字符，如果是，则返回当前转义字符的ASCII编码值。最后，使用luaZ_buffremove函数从输入的字符数组中移除读取的ASCII编码字符，并返回结果。

这两个函数一起工作，帮助用户处理UTF-8编码字符串，可以将输入的ASCII编码字符串转换为UTF-8编码字符串，并支持将ASCII转义字符转换为它们对应的UTF-8编码字符。


```
static void utf8esc (LexState *ls) {
  char buff[UTF8BUFFSZ];
  int n = luaO_utf8esc(buff, readutf8esc(ls));
  for (; n > 0; n--)  /* add 'buff' to string */
    save(ls, buff[UTF8BUFFSZ - n]);
}


static int readdecesc (LexState *ls) {
  int i;
  int r = 0;  /* result accumulator */
  for (i = 0; i < 3 && lisdigit(ls->current); i++) {  /* read up to 3 digits */
    r = 10*r + ls->current - '0';
    save_and_next(ls);
  }
  esccheck(ls, r <= UCHAR_MAX, "decimal escape too large");
  luaZ_buffremove(ls->buff, i);  /* remove read digits from buffer */
  return r;
}


```cpp

It looks like this is a Lua script that is meant to be used to process text files that contain a list of lines with some kind of text or formatting. It appears to be reading through the contents of the file, processing each line, and then writing a backup of the processed file.

The script uses several functions to handle different aspects of the text, such as reading a hexadecimal escape sequence (using the 'x'), converting text to a byte stream (using the 'u' escape sequence), and checking for the end of the file (using the 'E' escape sequence). It also uses a macro called 'read\_save' which is called with the next character after the last save in the file.

There is also a macro called 'no\_save' which is called if the current character is an escape sequence that is not a valid escape sequence, such as 'z' or 'zap'.

The script also includes a 'seminfo' variable which is used to keep track of information about the file, such as the line number and the file name.

Overall, it appears to be a relatively simple script designed to process text files, but it may not work for all types of text or formatting.


```
static void read_string (LexState *ls, int del, SemInfo *seminfo) {
  save_and_next(ls);  /* keep delimiter (for error messages) */
  while (ls->current != del) {
    switch (ls->current) {
      case EOZ:
        lexerror(ls, "unfinished string", TK_EOS);
        break;  /* to avoid warnings */
      case '\n':
      case '\r':
        lexerror(ls, "unfinished string", TK_STRING);
        break;  /* to avoid warnings */
      case '\\': {  /* escape sequences */
        int c;  /* final character to be saved */
        save_and_next(ls);  /* keep '\\' for error messages */
        switch (ls->current) {
          case 'a': c = '\a'; goto read_save;
          case 'b': c = '\b'; goto read_save;
          case 'f': c = '\f'; goto read_save;
          case 'n': c = '\n'; goto read_save;
          case 'r': c = '\r'; goto read_save;
          case 't': c = '\t'; goto read_save;
          case 'v': c = '\v'; goto read_save;
          case 'x': c = readhexaesc(ls); goto read_save;
          case 'u': utf8esc(ls);  goto no_save;
          case '\n': case '\r':
            inclinenumber(ls); c = '\n'; goto only_save;
          case '\\': case '\"': case '\'':
            c = ls->current; goto read_save;
          case EOZ: goto no_save;  /* will raise an error next loop */
          case 'z': {  /* zap following span of spaces */
            luaZ_buffremove(ls->buff, 1);  /* remove '\\' */
            next(ls);  /* skip the 'z' */
            while (lisspace(ls->current)) {
              if (currIsNewline(ls)) inclinenumber(ls);
              else next(ls);
            }
            goto no_save;
          }
          default: {
            esccheck(ls, lisdigit(ls->current), "invalid escape sequence");
            c = readdecesc(ls);  /* digital escape '\ddd' */
            goto only_save;
          }
        }
       read_save:
         next(ls);
         /* go through */
       only_save:
         luaZ_buffremove(ls->buff, 1);  /* remove '\\' */
         save(ls, c);
         /* go through */
       no_save: break;
      }
      default:
        save_and_next(ls);
    }
  }
  save_and_next(ls);  /* skip delimiter */
  seminfo->ts = luaX_newstring(ls, luaZ_buffer(ls->buff) + 1,
                                   luaZ_bufflen(ls->buff) - 2);
}


```cpp

This is a Java implementation of the `tkInt持` command provided by the Tagclash library. It reads a string or number from the input, depending on the current character, until it reaches the end of the input or the first character of an identifier or a reserved word. It then returns the appropriate value.


```
static int llex (LexState *ls, SemInfo *seminfo) {
  luaZ_resetbuffer(ls->buff);
  for (;;) {
    switch (ls->current) {
      case '\n': case '\r': {  /* line breaks */
        inclinenumber(ls);
        break;
      }
      case ' ': case '\f': case '\t': case '\v': {  /* spaces */
        next(ls);
        break;
      }
      case '-': {  /* '-' or '--' (comment) */
        next(ls);
        if (ls->current != '-') return '-';
        /* else is a comment */
        next(ls);
        if (ls->current == '[') {  /* long comment? */
          size_t sep = skip_sep(ls);
          luaZ_resetbuffer(ls->buff);  /* 'skip_sep' may dirty the buffer */
          if (sep >= 2) {
            read_long_string(ls, NULL, sep);  /* skip long comment */
            luaZ_resetbuffer(ls->buff);  /* previous call may dirty the buff. */
            break;
          }
        }
        /* else short comment */
        while (!currIsNewline(ls) && ls->current != EOZ)
          next(ls);  /* skip until end of line (or end of file) */
        break;
      }
      case '[': {  /* long string or simply '[' */
        size_t sep = skip_sep(ls);
        if (sep >= 2) {
          read_long_string(ls, seminfo, sep);
          return TK_STRING;
        }
        else if (sep == 0)  /* '[=...' missing second bracket? */
          lexerror(ls, "invalid long string delimiter", TK_STRING);
        return '[';
      }
      case '=': {
        next(ls);
        if (check_next1(ls, '=')) return TK_EQ;  /* '==' */
        else return '=';
      }
      case '<': {
        next(ls);
        if (check_next1(ls, '=')) return TK_LE;  /* '<=' */
        else if (check_next1(ls, '<')) return TK_SHL;  /* '<<' */
        else return '<';
      }
      case '>': {
        next(ls);
        if (check_next1(ls, '=')) return TK_GE;  /* '>=' */
        else if (check_next1(ls, '>')) return TK_SHR;  /* '>>' */
        else return '>';
      }
      case '/': {
        next(ls);
        if (check_next1(ls, '/')) return TK_IDIV;  /* '//' */
        else return '/';
      }
      case '~': {
        next(ls);
        if (check_next1(ls, '=')) return TK_NE;  /* '~=' */
        else return '~';
      }
      case ':': {
        next(ls);
        if (check_next1(ls, ':')) return TK_DBCOLON;  /* '::' */
        else return ':';
      }
      case '"': case '\'': {  /* short literal strings */
        read_string(ls, ls->current, seminfo);
        return TK_STRING;
      }
      case '.': {  /* '.', '..', '...', or number */
        save_and_next(ls);
        if (check_next1(ls, '.')) {
          if (check_next1(ls, '.'))
            return TK_DOTS;   /* '...' */
          else return TK_CONCAT;   /* '..' */
        }
        else if (!lisdigit(ls->current)) return '.';
        else return read_numeral(ls, seminfo);
      }
      case '0': case '1': case '2': case '3': case '4':
      case '5': case '6': case '7': case '8': case '9': {
        return read_numeral(ls, seminfo);
      }
      case EOZ: {
        return TK_EOS;
      }
      default: {
        if (lislalpha(ls->current)) {  /* identifier or reserved word? */
          TString *ts;
          do {
            save_and_next(ls);
          } while (lislalnum(ls->current));
          ts = luaX_newstring(ls, luaZ_buffer(ls->buff),
                                  luaZ_bufflen(ls->buff));
          seminfo->ts = ts;
          if (isreserved(ts))  /* reserved word? */
            return ts->extra - 1 + FIRST_RESERVED;
          else {
            return TK_NAME;
          }
        }
        else {  /* single-char tokens ('+', '*', '%', '{', '}', ...) */
          int c = ls->current;
          next(ls);
          return c;
        }
      }
    }
  }
}


```cpp

这两段代码是针对Lua虚拟机中的一个名为"luaX_next"的函数和名为"luaX_lookahead"的函数。

函数"luaX_next"的作用是每当从输入流中读取到一个字符时，更新"lastline"变量并检查是否读取到了输入流中的最后一个字符('\0')，如果是，则使用一个存储当前 lookahead 位置的 token，并将其覆盖为'\0'。"lastline"变量保存了输入行号，每次更新时会将当前行号更新为之前记录的行号。

函数"luaX_lookahead"的作用是在 Lua 源文件中进行输入定位时使用的函数。该函数首先检查输入流中是否有可读取的 lookahead token(即 EOF token)，如果没有，则从输入流中读取下一个 token。如果有一个可读取的 lookahead token，则将其存储在"lookahead"变量中，并返回它。


```
void luaX_next (LexState *ls) {
  ls->lastline = ls->linenumber;
  if (ls->lookahead.token != TK_EOS) {  /* is there a look-ahead token? */
    ls->t = ls->lookahead;  /* use this one */
    ls->lookahead.token = TK_EOS;  /* and discharge it */
  }
  else
    ls->t.token = llex(ls, &ls->t.seminfo);  /* read next token */
}


int luaX_lookahead (LexState *ls) {
  lua_assert(ls->lookahead.token == TK_EOS);
  ls->lookahead.token = llex(ls, &ls->lookahead.seminfo);
  return ls->lookahead.token;
}


```cpp

# `liblua/llimits.h`

这段代码是一个C语言预处理指令，它定义了一个名为"llimits_h"的文件。这个文件的作用是包含一些定义，包括限制、基本数据类型以及一些与安装相关的定义。

具体来说，这个文件包含了以下内容：

1. 定义了"__REQUIRED_INPUT"宏，它是一个C语言预处理指令，用于告诉编译器在编译之前需要输入的内容。这个宏通常是用来告诉编译器有一些定义是必需的，这样就可以避免编译错误。

2. 定义了"__PD"宏，它也是一个C语言预处理指令，用于告诉编译器在编译之前需要避免的指令。这个宏通常是用来告诉编译器有一些指令是危险的，这样就可以避免编译错误。

3. 定义了一些函数，包括：@aes_64, @ascii_Lowercase, @ascii_Uppercase, @ascii_T lowercase, @ascii_Uppercase, @ascii_ToLowercase, @ascii_ToUppercase, @ascii_ToChars, @ascii_ToWords, @ascii_ToSymbols, @ascii_ToDateTime, @ascii_ToUrl, @ascii_ToCharCode, @ascii_ToUnicode, @ascii_ToWideChar。

4. 引入了一些C语言标准库头文件，包括：<stddef.h>，<math.h>，<isalib.h>，<intrins.h>，<指導 fdpsr 电工 >。

5. 使用包含从"lua.h"中包含的定义。


```
/*
** $Id: llimits.h $
** Limits, basic types, and some other 'installation-dependent' definitions
** See Copyright Notice in lua.h
*/

#ifndef llimits_h
#define llimits_h


#include <limits.h>
#include <stddef.h>


#include "lua.h"


```cpp

这段代码定义了两种类型的整型变量lu_mem和l_mem，它们的值 大于 Lua 中能使用的最大字节数。通常，'size_t' 和 'ptrdiff_t' 应该可以工作，但是该代码使用 'long' 作为 16 位机器的值。

接下来，代码根据定义的 Lua 变量类型来定义 lu_mem 和 l_mem 变量。如果定义的是 Lua 的定义变量，那么 lu_mem 和 l_mem 将具有默认值 0。

最后，代码使用条件语句检查定义的变量是否为 16 位整数。如果是，那么 lu_mem 和 l_mem 的定义将成功，否则会抛出错误。


```
/*
** 'lu_mem' and 'l_mem' are unsigned/signed integers big enough to count
** the total memory used by Lua (in bytes). Usually, 'size_t' and
** 'ptrdiff_t' should work, but we use 'long' for 16-bit machines.
*/
#if defined(LUAI_MEM)		/* { external definitions? */
typedef LUAI_UMEM lu_mem;
typedef LUAI_MEM l_mem;
#elif LUAI_IS32INT	/* }{ */
typedef size_t lu_mem;
typedef ptrdiff_t l_mem;
#else  /* 16-bit ints */	/* }{ */
typedef unsigned long lu_mem;
typedef long l_mem;
#endif				/* } */


```cpp

这段代码定义了一些数据类型，包括：

- lu_byte：无符号字节类型，可以表示0到255之间的整数。
- ls_byte：有符号字节类型，可以表示0到255之间的整数。

还定义了一些常量，包括：

- MAX_SIZET：最大size_t类型数据类型的大小，使用了size_t的有符号整数能够表示的最大值 - 0。
- MAX_SIZE：Lua中可见的最大size类型数据类型的大小，必须小于size_t的有符号整数能够表示的最大值。
- MAX_LUMEM：Lua中可见的最大内存类型数据类型的大小，使用了size_t的无符号整数能够表示的最大值 - 0。

最后，还定义了一个名为MAX_LUMEM的函数，返回值为最大内存类型数据类型的大小。


```
/* chars used as small naturals (so that 'char' is reserved for characters) */
typedef unsigned char lu_byte;
typedef signed char ls_byte;


/* maximum value for size_t */
#define MAX_SIZET	((size_t)(~(size_t)0))

/* maximum size visible for Lua (must be representable in a lua_Integer) */
#define MAX_SIZE	(sizeof(size_t) < sizeof(lua_Integer) ? MAX_SIZET \
                          : (size_t)(LUA_MAXINTEGER))


#define MAX_LUMEM	((lu_mem)(~(lu_mem)0))

```cpp

This code defines several macros with placeholders for expansion.

1. `#define MAX_LMEM	((l_mem)(MAX_LUMEM >> 1))`: This macro defines a macro called `MAX_LMEM` that takes a single parameter `l_mem`. It uses this parameter to cast `MAX_LUMEM` to a long long memory location, and then extracts the least significant byte (LSB) to remove the sign of the value. This is defined in the `.h` file as `MAX_LMEM = MAX_LUMEM & -MAX_LUMEM_BIT,` but for some platforms and compilers, this may be defined directly in the `.c` file.

2. `#define MAX_INT		INT_MAX`: This macro defines a macro called `MAX_INT` that takes no parameters. It defines the largest value that can be represented by an `int` data type on the platform.

3. `#define log2maxs(t)	(sizeof(t) * 8 - 2)`: This macro defines a macro called `log2maxs` that takes a single parameter `t`. It uses this parameter to calculate the floor of the log2 of the maximum signed value for the integral type `t`. This is the maximum value `t` can have for its data type.

4. `#define EMPTY_Macro(name)	Macro_Name[0] = ' ';`: This macro defines an empty macro called `EMPTY_Macro`, but it does not provide any implementation. It takes a single parameter `name`, which is an empty string. It replaces any spaces in the argument with an empty string.

5. `#define MAX_LUMEM_BIT		0x80000000`: This macro defines a macro called `MAX_LUMEM_BIT` that returns the bit pattern representation of `MAX_LUMEM` as a single line of code.


```
#define MAX_LMEM	((l_mem)(MAX_LUMEM >> 1))


#define MAX_INT		INT_MAX  /* maximum value of an int */


/*
** floor of the log2 of the maximum signed value for integral type 't'.
** (That is, maximum 'n' such that '2^n' fits in the given signed type.)
*/
#define log2maxs(t)	(sizeof(t) * 8 - 2)


/*
** test whether an unsigned value is a power of 2 (or zero)
```cpp



这段代码定义了三个宏，分别用于计算一个数的阶乘、一个字符串中字符的数量、和一个指针变量与整型变量之间的转换。

ispow2(x)是一个宏，用于计算一个整数x的阶乘，其逻辑为：如果x是一个非负整数，则ispow2(x)等于1；否则，ispow2(x)等于0。

LL(x)是一个宏，用于计算一个字符串x中字符的数量，其逻辑为：将x中的字符数除以字符数大小，再减去1，得到的结果就是LL(x)。

point2uint(p)是一个宏，用于将一个指针变量p转换为整型变量，其逻辑为：将p的值从整型变量中解析为无符号整型，得到的结果就是point2uint(p)。

总结起来，这段代码定义了三个宏，用于计算阶乘、字符串中字符的数量以及指针变量与整型变量之间的转换。这些宏可以方便地在程序中进行使用，减少代码的冗长度和难以理解的情况。


```
*/
#define ispow2(x)	(((x) & ((x) - 1)) == 0)


/* number of chars of a literal string without the ending \0 */
#define LL(x)   (sizeof(x)/sizeof(char) - 1)


/*
** conversion of pointer to unsigned integer:
** this is for hashing only; there is no problem if the integer
** cannot hold the whole pointer value
*/
#define point2uint(p)	((unsigned int)((size_t)(p) & UINT_MAX))



```cpp

这段代码定义了一些类型别名，用于将Lua中的`lua_Number`和`lua_Integer`类型别名转换为Java中的`int`和`long`类型。

同时，代码中包含了一些内部assert语句，用于在调试时进行assert语句的检查，以确保程序在某些情况下能够正常运行。这些assert语句可能会在程序的编译、链接或运行过程中产生警告，但不会影响程序的运行。


```
/* types of 'usual argument conversions' for lua_Number and lua_Integer */
typedef LUAI_UACNUMBER l_uacNumber;
typedef LUAI_UACINT l_uacInt;


/*
** Internal assertions for in-house debugging
*/
#if defined LUAI_ASSERT
#undef NDEBUG
#include <assert.h>
#define lua_assert(c)           assert(c)
#endif

#if defined(lua_assert)
```cpp

这段代码定义了一系列的函数和宏，主要作用是定义和实现了一个名为`luai_apicheck`的函数，用于检查API调用的返回值是否符合预期。下面是对这些函数和宏的解释：

1. `#define check_exp(c,e) (e)`
  这是一个宏定义，用于定义一个名为`check_exp`的函数，该函数有两个参数，一个整型变量`c`和一个布尔型变量`e`。这个宏定义的作用是在编译时将`e`的值复制一份给`check_exp`函数的参数。

2. `#define lua_longassert(c) ((void)0)`
  这是一个宏定义，用于定义一个名为`lua_longassert`的函数，该函数有一个整型参数`c`。这个宏定义的作用是在编译时将`c`的值复制一份给`lua_longassert`函数的参数，并在函数内部将`c`的值初始化为`0`。

3. `#else`
  这是一个多行注释，表示如果`#define`后面的定义有任何一行被注释，则以下定义都不会生效。

4. `#define lua_assert(c) (void)`
  这是一个宏定义，用于定义一个名为`lua_assert`的函数，该函数有一个整型参数`c`。这个宏定义的作用是在编译时将`c`的值复制一份给`lua_assert`函数的参数，并在函数内部将`c`的值初始化为`0`。

5. `#define check_exp(c,e) (e)`
  这是一个宏定义，用于定义一个名为`check_exp`的函数，该函数有两个整型参数，一个整型变量`c`和一个布尔型变量`e`。这个宏定义的作用是在编译时将`e`的值复制一份给`check_exp`函数的参数。


```
#define check_exp(c,e)		(lua_assert(c), (e))
/* to avoid problems with conditions too long */
#define lua_longassert(c)	((c) ? (void)0 : lua_assert(0))
#else
#define lua_assert(c)		((void)0)
#define check_exp(c,e)		(e)
#define lua_longassert(c)	((void)0)
#endif

/*
** assertion for checking API calls
*/
#if !defined(luai_apicheck)
#define luai_apicheck(l,e)	((void)l, lua_assert(e))
#endif

```cpp

这段代码定义了一系列的宏，用于检查函数参数和返回值是否被正确使用，以及进行类型转换等操作。

首先看到的是`api_check`，这是一个带参数的定义，它的作用是检查函数`l`和`e`以及传递给它的第三个参数`msg`是否都被正确地使用了。如果参数`e`是一个变量，那么这个函数会检查`l`是否被正确地引用，并且`msg`是否被正确地传递给`l`。如果参数`e`是一个表达式，那么这个函数会检查这个表达式的值是否为真，并且`msg`是否被正确地传递给`l`。如果参数`e`是一个已定义的函数，那么这个函数会检查`l`是否被正确地调用，并且`msg`是否被正确地传递给这个函数。

接着看到的是`UNUSED`定义，用于避免在使用但未经定义的变量时产生的警告。这个定义包含一个带参数的宏，它的作用是在定义变量时产生一个警告，警告的内容是提示这个变量已经被定义过，但不知道是何时定义的。

最后看到的是三个cast类型的定义，用于进行类型转换。其中`cast`类型的作用是返回一个与传入参数类型相同的值，`cast_void`类型的作用是返回一个`void`类型的值，这个值会被自动存储到`i`变量的地址上，`cast_voidp`类型的作用是返回一个`void *`类型的值，这个值会被自动存储到`i`变量的地址上，`cast_num`类型的作用是返回一个`lua_Number`类型的值，这个值会被自动存储到`i`变量的地址上。


```
#define api_check(l,e,msg)	luai_apicheck(l,(e) && msg)


/* macro to avoid warnings about unused variables */
#if !defined(UNUSED)
#define UNUSED(x)	((void)(x))
#endif


/* type casts (a macro highlights casts in the code) */
#define cast(t, exp)	((t)(exp))

#define cast_void(i)	cast(void, (i))
#define cast_voidp(i)	cast(void *, (i))
#define cast_num(i)	cast(lua_Number, (i))
```cpp

这段代码定义了一系列 cast 函数，用于将不同类型的 lua_Integer 数据类型转换为 lua_Unsigned、lua_Integer 等数据类型。

具体来说，这些函数接受一个 lua_Integer 参数 i，然后返回相应的 lua_Unsigned、lua_Integer 类型。如果定义了对应的函数，则直接使用函数名称，否则会使用 l_castS2U 函数进行强制转换。

例如，如果要将 lua_Integer 数据类型转换为 lua_Unsigned 类型，可以使用 l_castS2U 函数，如下所示：

```lua
local i = 123
local u = l_castS2U(i)
```cpp

这段代码会输出 123，因为 i 的值为 123，是一个 lua_Integer 数据类型。而 u 变量是一个 lua_Unsigned 类型，因为 l_castS2U 函数将其转换为了 lua_Unsigned 类型。


```
#define cast_int(i)	cast(int, (i))
#define cast_uint(i)	cast(unsigned int, (i))
#define cast_byte(i)	cast(lu_byte, (i))
#define cast_uchar(i)	cast(unsigned char, (i))
#define cast_char(i)	cast(char, (i))
#define cast_charp(i)	cast(char *, (i))
#define cast_sizet(i)	cast(size_t, (i))


/* cast a signed lua_Integer to lua_Unsigned */
#if !defined(l_castS2U)
#define l_castS2U(i)	((lua_Unsigned)(i))
#endif

/*
```cpp

This code defines a function `l_castU2S` that converts a `lua_Unsigned` value to a `lua_Integer` value. This function is not strict conforming to the ISO C standard, but two-complement architectures should still work fine.

The function takes an integer `i` as an argument and returns a `lua_Integer` value. If the `lua_Unsigned` value `i` is not defined, the function will simply return `(lua_Integer)i`, which is equivalent to casting a `lua_Unsigned` value to a `lua_Integer`.

The function is defined with the non-return type `#define l_castU2S(i) (lua_Integer)(i)` which means that the function has no return type and it will return only an integer value.

The code also includes a non-return type definition `#if !defined(l_noret)` which checks if the `l_noret` define has been defined. If it has not been defined, the code will skip the non-return type definition and the function will have no explicit return type.


```
** cast a lua_Unsigned to a signed lua_Integer; this cast is
** not strict ISO C, but two-complement architectures should
** work fine.
*/
#if !defined(l_castU2S)
#define l_castU2S(i)	((lua_Integer)(i))
#endif


/*
** non-return type
*/
#if !defined(l_noret)

#if defined(__GNUC__)
```cpp

这段代码是一个C语言预处理指令，用于定义一个名为`l_noret`的函数。它的作用是在编译时检查源代码中是否定义了这个函数，如果定义了，则替换定义体为函数体，否则输出"#error"。

具体来说，代码中使用了两种预处理指令：`#define`和`#elif`。`#define`后面跟一个`#define`号，表示后面的是一个定义，而不是一个表达式。它可以定义一个常量，后面可以跟一个标识符，表示该标识符的定义后面会出现的符号，替换为定义体。比如第一个例子中，`l_noret`就是一个定义，后面跟着的是一个`void`标识符，表示后面会出现一个`void`类型的函数体。

第二个例子中，预处理指令`#elif`表示后面是一个条件语句，判断条件成立的话，执行预处理指令后面的内容，否则跳过该预处理指令。在这个例子中，条件表达式是`_MSC_VER >= 1200`，表示判断当前编译器是否支持C++12或更高版本。如果版本高于或等于1200，则执行`#define`后面的内容，否则执行`#else`后面的内容。

如果预处理指令后面的标识符已经被定义，则替换为定义体。否则会输出"#error"，表示编译器无法处理该标识符，需要给出错误信息。


```
#define l_noret		void __attribute__((noreturn))
#elif defined(_MSC_VER) && _MSC_VER >= 1200
#define l_noret		void __declspec(noreturn)
#else
#define l_noret		void
#endif

#endif


/*
** Inline functions
*/
#if !defined(LUA_USE_C89)
#define l_inline	inline
```cpp

这段代码定义了一些符号常量，用于控制程序的某些方面。下面是每个符号常量的说明：

```
#elif defined(__GNUC__)
#define l_inline    **这是一个虚拟函数声明，表示如果定义了 __GNUC__，那么编译器会按照 __GNUC__ 的规则定义这个函数。**/
#else
#define l_inline    **如果没有定义 __GNUC__，那么编译器不会定义这个函数。**/
```cpp

```
#define l_sinline    static l_inline
```cpp

```
#define l_cosline    static l_inline
```cpp

```
#if LUAI_IS32INT
typedef unsigned int l_uint32;
```cpp

这段代码的作用是定义了两个虚拟函数，`l_inline` 和 `l_sinline` 和 `l_cosline`，用于计算数学的`sin`和`cos`函数。`l_uint32` 是一个`unsigned int`类型的变量，用于表示一个无符号32位整数。


```
#elif defined(__GNUC__)
#define l_inline	__inline__
#else
#define l_inline	/* empty */
#endif

#define l_sinline	static l_inline


/*
** type for virtual-machine instructions;
** must be an unsigned with (at least) 4 bytes (see details in lopcodes.h)
*/
#if LUAI_IS32INT
typedef unsigned int l_uint32;
```cpp

这段代码定义了一个名为 l_uint32 的无符号长整型变量，并定义了一个名为 Instruction 的无符号长整型指针类型，该指针类型继承自 l_uint32 类型。

接下来的两行代码检查是否定义了名为 "function" 和 "__newindex" 的保留函数，如果是，则定义了一个名为 l_uint32 的内部化函数。这个函数的最大长度目前被定义为 8，可以根据需要在代码中修改。

最后一行代码是一个注释，用于在没有定义 "function" 和 "__newindex" 函数的情况下，给出编译器错误信息。


```
#else
typedef unsigned long l_uint32;
#endif

typedef l_uint32 Instruction;



/*
** Maximum length for short strings, that is, strings that are
** internalized. (Cannot be smaller than reserved words or tags for
** metamethods, as these strings must be internalized;
** #("function") = 8, #("__newindex") = 10.)
*/
#if !defined(LUAI_MAXSHORTLEN)
```cpp

这段代码是一个C/C++语言的预处理指令，定义了一些用于Lua静态代码生成的参数和常量。

第一个定义是`LUAI_MAXSHORTLEN`，表示Lua中字符串的最大长度，定义为40。

第二个定义是`#ifdef !defined(MINSTRTABSIZE)`，表示如果这个预处理指令已经被定义过了，就跳过这个指令，否则定义一个名为`MINSTRTABSIZE`的常量，值为128。这个常量表示Lua中字符串表的最小大小，必须是2的幂次方。

接下来的两个定义与Lua的字符串表相关，定义了`MINSTRTABSIZE`和`LUAI_MAXSHORTLEN`的值，使得字符串表的大小为40，也就是Lua中字符串的最大长度为40个字符。

最后，通过`#if !defined(MINSTRTABSIZE)`这个条件编译，如果这个预处理指令已经被定义过了，则不执行第一个定义，否则执行第二个定义，定义了一个名为`MINSTRTABSIZE`的常量，值为128，与前面的定义保持一致。


```
#define LUAI_MAXSHORTLEN	40
#endif


/*
** Initial size for the string table (must be power of 2).
** The Lua core alone registers ~50 strings (reserved words +
** metaevent keys + a few others). Libraries would typically add
** a few dozens more.
*/
#if !defined(MINSTRTABSIZE)
#define MINSTRTABSIZE	128
#endif


```cpp

这段代码定义了一个名为`STRCACHE_N`和`STRCACHE_M`的宏，用于指定缓存中字符串集的数量和每个字符串集的大小。如果这个定义在函数外部，则可以用来定义全局变量，否则无法访问它们。

接下来，代码中定义了一个名为`LUA_MINBUFFER`的宏，用于指定最小字符串缓冲区大小。这个宏同样也可以在函数外部被定义，否则无法访问它。

最后，该代码没有定义任何函数或执行任何操作，因此它对程序的运行不会产生任何影响。


```
/*
** Size of cache for strings in the API. 'N' is the number of
** sets (better be a prime) and "M" is the size of each set (M == 1
** makes a direct cache.)
*/
#if !defined(STRCACHE_N)
#define STRCACHE_N		53
#define STRCACHE_M		2
#endif


/* minimum size for string buffer */
#if !defined(LUA_MINBUFFER)
#define LUA_MINBUFFER	32
#endif


```cpp

这段代码定义了一个名为`LUAI_MAXCCALLS`的 macro，它的值为200。这个 macro 使用了 recursion，通过它可以检查多层嵌套的 C 函数的最大深度以及实现其他功能。同时，它还定义了一个名为`LUAI_MAXCCALLS`的宏，它的值为16位无符号整数，用于存储函数的最大深度。

此外，代码中还有一段注释，它提到了一个名为`LUAI_MAXCCALLS`的宏，但并未提供更多详细信息。

另外，代码中还有一段注释，它提到了一个名为`__attribute__((const))`的注解，但同样未提供更多详细信息。


```
/*
** Maximum depth for nested C calls, syntactical nested non-terminals,
** and other features implemented through recursion in C. (Value must
** fit in a 16-bit unsigned integer. It must also be compatible with
** the size of the C stack.)
*/
#if !defined(LUAI_MAXCCALLS)
#define LUAI_MAXCCALLS		200
#endif


/*
** macros that are executed whenever program enters the Lua core
** ('lua_lock') and leaves the core ('lua_unlock')
*/
```cpp

这段代码是一个C语言和Lua脚本语言的互操作代码。它定义了一些宏，用于在Lua函数中设置和取消对内存的锁定。

`#if !defined(lua_lock)`和`#define lua_lock(L)`定义了一个名为`lua_lock`的函数，它的参数`L`代表要锁定的对象。如果该函数已定义，则其作用域为`__alpha__`。否则，它会定义一个与`#define`相同的语句，但参数中少了`__alpha__`。

`#define lua_unlock(L)`和`#define lua_unlock(L)`定义了名为`lua_unlock`的函数，它的参数`L`代表要解锁的对象。这两个函数在定义时会使用与`#define`相同的语句，但参数中少了`__alpha__`。

`#if !defined(luai_threadyield)`定义了一个名为`luai_threadyield`的函数。它的作用域为`__alpha__`。如果没有定义该函数，则该语句会输出一个警告。如果该函数定义了，则会编译出包含该函数的代码。

`#define luai_thready yield(luai_thready)`定义了一个名为`luai_thready`的函数，它的参数是一个函数指针。由于`luai_thREADY`是一个已定义的函数，所以该函数指针会被Lua识别为函数名称。因此，`luai_thready`函数会被约束为`function luai_thready`。

综合来看，这段代码定义了一些与Lua锁定和解除有关的函数，以及定义了一些与Lua `__alpha__` 函数有关的头文件。


```
#if !defined(lua_lock)
#define lua_lock(L)	((void) 0)
#define lua_unlock(L)	((void) 0)
#endif

/*
** macro executed during Lua functions at points where the
** function can yield.
*/
#if !defined(luai_threadyield)
#define luai_threadyield(L)	{lua_unlock(L); lua_lock(L);}
#endif


/*
```cpp

这段代码定义了几个 macro，用于在创建、删除、重启或暂停线程时执行用户特定的操作。如果没有定义这些宏，你需要显式地定义它们。

```
#if !defined(luai_userstateopen)
#define luai_userstateopen(L)		((void)L)
#endif

#if !defined(luai_userstateclose)
#define luai_userstateclose(L)		((void)L)
#endif

#if !defined(luai_userstatethread)
#define luai_userstatethread(L,L1)	((void)L)
#endif
```cpp

这段代码会定义三个宏：`luai_userstateopen`、`luai_userstateclose` 和 `luai_userstatethread`。这三个宏分别用于执行创建线程、关闭线程和暂停线程时的用户特定操作。当线程被创建或销毁时，这些宏会接受用户提供的参数作为第一个参数。

注意：这段代码是在 Linux 系统下定义的，所以如果你在不同的系统上使用，可能需要对代码进行修改。


```
** these macros allow user-specific actions when a thread is
** created/deleted/resumed/yielded.
*/
#if !defined(luai_userstateopen)
#define luai_userstateopen(L)		((void)L)
#endif

#if !defined(luai_userstateclose)
#define luai_userstateclose(L)		((void)L)
#endif

#if !defined(luai_userstatethread)
#define luai_userstatethread(L,L1)	((void)L)
#endif

```cpp

这段代码定义了三个宏，分别代表不同的状态。如果当前用户态处于空闲状态，则这三个宏分别返回当前用户态的内存空间，否则会抛出异常。

宏定义如下：
```bash
#if !defined(luai_userstatefree)
#define luai_userstatefree(L)	((void)L)
#endif

#if !defined(luai_userstateresume)
#define luai_userstateresume(L,n)	((void)L)
#endif

#if !defined(luai_userstateyield)
#define luai_userstateyield(L,n)	((void)L)
#endif
```cpp
- `luai_userstatefree`：如果当前用户态为空闲状态，则返回当前用户态的内存空间。否则会抛出异常。
- `luai_userstateresume`：如果当前用户态为空闲状态，则返回当前用户态的内存空间。否则会抛出异常。
- `luai_userstateyield`：如果当前用户态为空闲状态，则返回当前用户态的内存空间。否则会抛出异常。


```
#if !defined(luai_userstatefree)
#define luai_userstatefree(L,L1)	((void)L)
#endif

#if !defined(luai_userstateresume)
#define luai_userstateresume(L,n)	((void)L)
#endif

#if !defined(luai_userstateyield)
#define luai_userstateyield(L,n)	((void)L)
#endif



/*
```cpp

这段代码定义了一些在Lua中操作数字的基本操作符，包括向下取整（floor）和浮点数除法（div）以及取模（mod）操作。

向下取整（floor）的作用是，将一个数值a除以另一个数值b，然后将结果l求出来。如果a除以b的余数大于或等于0，那么l的值就等于a除以b向下取整的结果；否则，l的值就是a除以b向下取整的结果减去0.5。

浮点数除法（div）的作用是，将一个浮点数L除以另一个浮点数a，然后将结果d求出来。如果a除以b的余数为0，那么d的值就等于a除以b的结果。

取模（mod）操作的作用是，将一个整数L除以另一个整数a，然后将结果保持为l，直到a除以b的余数等于0。

注意，这些操作符都有特定的实现方式，具体取决于所使用的操作系统和Lua的版本。在这段代码中，我们使用了来自luai库的 macros，来定义这些操作符。如果没有使用这些macros，需要在编译时提供相应的定义，否则就会出现错误。


```
** The luai_num* macros define the primitive operations over numbers.
*/

/* floor division (defined as 'floor(a/b)') */
#if !defined(luai_numidiv)
#define luai_numidiv(L,a,b)     ((void)L, l_floor(luai_numdiv(L,a,b)))
#endif

/* float division */
#if !defined(luai_numdiv)
#define luai_numdiv(L,a,b)      ((a)/(b))
#endif

/*
** modulo: defined as 'a - floor(a/b)*b'; the direct computation
```cpp

这段代码定义了一个名为 `luai_nummod` 的函数，用于计算浮点数除法时的向下取整或向上取整。

函数有两个参数：`L` 是浮点数类型，表示要计算的浮点数；`a` 是被除数，浮点数类型；`b` 是除数，浮点数类型。函数还有一个参数 `m`，表示计算得到的向下取整或向上取整的整数部分。

函数首先定义了一个入口函数 `(void)luai_nummod(L,a,b,m)`，用于计算向下取整或向上取整的整数部分，这个函数内部实现了 `l_mathop(fmod)` 函数，这个函数接收三个参数： `a` 和 `b` 是两个浮点数，表示要计算的整数部分和分母；`m` 是整数部分，输出参数。

如果 `m` 大于 0，说明 `a` 小于 `b`，这时候向下取整得到的结果是 `b`，所以代码中这样写：
```css
   (m) = l_mathop(fmod)(a,b); 
   if (((m) > 0) ? (b) < 0 : ((m) < 0 && (b) > 0)) (m) += (b); 
```cpp
如果 `m` 小于 0，说明 `a` 大于 `b`，这时候向下取整得到的结果是 `a`，所以代码中这样写：
```css
   (m) = l_mathop(fmod)(a,b); 
   if (((m) < 0) && (b) > 0) (m) += (b); 
   if (((m) > 0) ? (b) < 0 : ((m) < 0 && (b) < 0)) (m) -= (b); 
```cpp
如果 `m` 等于 0，说明 `a` 和 `b` 相等，这时候向下取整或向上取整都不会产生错误的结果，所以代码中这样写：
```css
   (m) = l_mathop(fmod)(a,b); 
   if (((m) > 0) ? (b) < 0 : ((m) < 0 && (b) > 0)) (m) += (b); 
   if (((m) < 0) && (b) < 0) (m) -= (b); 
   (m) = 0; 
```cpp
最后，如果 `L` 没有被定义，或者 `luai_nummod` 函数没有被定义，代码会抛出 `std::invalid_argument` 异常。


```
** using this definition has several problems with rounding errors,
** so it is better to use 'fmod'. 'fmod' gives the result of
** 'a - trunc(a/b)*b', and therefore must be corrected when
** 'trunc(a/b) ~= floor(a/b)'. That happens when the division has a
** non-integer negative result: non-integer result is equivalent to
** a non-zero remainder 'm'; negative result is equivalent to 'a' and
** 'b' with different signs, or 'm' and 'b' with different signs
** (as the result 'm' of 'fmod' has the same sign of 'a').
*/
#if !defined(luai_nummod)
#define luai_nummod(L,a,b,m)  \
  { (void)L; (m) = l_mathop(fmod)(a,b); \
    if (((m) > 0) ? (b) < 0 : ((m) < 0 && (b) > 0)) (m) += (b); }
#endif

```cpp

这段代码定义了一系列数学函数，包括：

- luai_numpow：将传入的参数a和b进行乘方运算，并返回结果。如果b为2，则首先计算a的平方，否则使用pow函数进行计算。
- luai_numadd：将传入的参数a和b进行加法运算，并返回结果。
- luai_numsub：将传入的参数a和b进行减法运算，并返回结果。
- luai_nummul：将传入的参数a和b进行乘法运算，并返回结果。
- luai_numunm：将传入的参数a进行取反运算，并返回结果。
- luai_numeq：比较两个参数a和b是否相等，并返回一个整数类型的值。
- luai_numlt：比较两个参数a和b是否大小关系，并返回一个整数类型的值。


```
/* exponentiation */
#if !defined(luai_numpow)
#define luai_numpow(L,a,b)  \
  ((void)L, (b == 2) ? (a)*(a) : l_mathop(pow)(a,b))
#endif

/* the others are quite standard operations */
#if !defined(luai_numadd)
#define luai_numadd(L,a,b)      ((a)+(b))
#define luai_numsub(L,a,b)      ((a)-(b))
#define luai_nummul(L,a,b)      ((a)*(b))
#define luai_numunm(L,a)        (-(a))
#define luai_numeq(a,b)         ((a)==(b))
#define luai_numlt(a,b)         ((a)<(b))
#define luai_numle(a,b)         ((a)<=(b))
```cpp

这段代码定义了一系列宏，用于实现对栈再分配的测试。

首先，栈再分配指的是在栈上分配内存时，判断栈是否可以再分配，如果可以，就输出一条预备语句，否则输出一条提示消息。

luai_numgt、luai_numge和luai_numisnan是三个测试函数，用于测试栈上分配内存时的不同情况。

luai_numgt函数的作用是判断a是否大于b，如果是，则输出"a>b"，如果不是，则输出"a<b"。

luai_numge函数的作用是判断a是否大于或等于b，如果是，则输出"a>=b"，如果不是，则输出"a<=b"。

luai_numisnan函数的作用是判断给定的a是否为NaN，如果是，则输出"！"，如果不是，则不做任何处理。

整个函数可以看作是对栈再分配时的一些辅助判断，用于保证在栈上分配内存时，能够正确处理各种情况。


```
#define luai_numgt(a,b)         ((a)>(b))
#define luai_numge(a,b)         ((a)>=(b))
#define luai_numisnan(a)        (!luai_numeq((a), (a)))
#endif





/*
** macro to control inclusion of some hard tests on stack reallocation
*/
#if !defined(HARDSTACKTESTS)
#define condmovestack(L,pre,pos)	((void)0)
#else
```cpp

这段代码定义了两个C函数：condmovestack和condchangemem。函数的作用是实现栈的重新分配和变化。

condmovestack函数接收三个参数：一个整型指针L，一个指向整型数据的pre指向，一个指向int类型数据的pos。函数内部首先调用stacksize函数来获取栈当前的大小，然后使用luaD_reallocstack函数重新分配内存空间，将栈大小增加到预设大小，最后将pos所指向的位置作为新的栈顶位置。

condchangemem函数与condmovestack函数类似，但有一个重要的区别，当函数检测到垃圾回收器正在运行时，函数将不会执行任何内存操作，而仅仅是返回一个void类型的值，表示操作成功。否则，函数会根据当前栈的大小和位置，以及当前垃圾回收器的状态来执行相应的内存操作，包括重新分配和释放内存等。

这两函数的具体实现可能会在具体的编程语言或库中有所不同，但它们的核心功能是相同的，即实现栈的重新分配和变化。


```
/* realloc stack keeping its size */
#define condmovestack(L,pre,pos)  \
  { int sz_ = stacksize(L); pre; luaD_reallocstack((L), sz_, 0); pos; }
#endif

#if !defined(HARDMEMTESTS)
#define condchangemem(L,pre,pos)	((void)0)
#else
#define condchangemem(L,pre,pos)  \
	{ if (gcrunning(G(L))) { pre; luaC_fullgc(L, 0); pos; } }
#endif

#endif

```